aio_wiki/__init__.py
aio_wiki/exceptions.py
aio_wiki/http_client.py
aio_wiki/wikidata.py
aio_wiki/wikimedia.py
aio_wiki-0.1.0.dist-info/METADATA
aio_wiki-0.1.0.dist-info/RECORD
aio_wiki-0.1.0.dist-info/WHEEL
aio_wiki-0.1.0.dist-info/top_level.txt
